{
  "avif": [
    {
      "format": "avif",
      "width": 90,
      "height": 94,
      "url": "/img/avatars/opencollective/oof.avif",
      "sourceType": "image/avif",
      "srcset": "/img/avatars/opencollective/oof.avif 90w",
      "filename": "oof.avif",
      "outputPath": "img/avatars/opencollective/oof.avif",
      "size": 2035
    }
  ],
  "webp": [
    {
      "format": "webp",
      "width": 90,
      "height": 94,
      "url": "/img/avatars/opencollective/oof.webp",
      "sourceType": "image/webp",
      "srcset": "/img/avatars/opencollective/oof.webp 90w",
      "filename": "oof.webp",
      "outputPath": "img/avatars/opencollective/oof.webp",
      "size": 3062
    }
  ],
  "jpeg": [
    {
      "format": "jpeg",
      "width": 90,
      "height": 94,
      "url": "/img/avatars/opencollective/oof.jpeg",
      "sourceType": "image/jpeg",
      "srcset": "/img/avatars/opencollective/oof.jpeg 90w",
      "filename": "oof.jpeg",
      "outputPath": "img/avatars/opencollective/oof.jpeg",
      "size": 3297
    }
  ],
  "slug": "oof"
}