{
  "webp": [
    {
      "format": "webp",
      "width": 90,
      "height": 90,
      "url": "/img/avatars/twitter/9b4109d9-90.webp",
      "sourceType": "image/webp",
      "srcset": "/img/avatars/twitter/9b4109d9-90.webp 90w",
      "outputPath": "img/avatars/twitter/9b4109d9-90.webp",
      "size": 2774
    }
  ],
  "jpeg": [
    {
      "format": "jpeg",
      "width": 90,
      "height": 90,
      "url": "/img/avatars/twitter/9b4109d9-90.jpeg",
      "sourceType": "image/jpeg",
      "srcset": "/img/avatars/twitter/9b4109d9-90.jpeg 90w",
      "outputPath": "img/avatars/twitter/9b4109d9-90.jpeg",
      "size": 3158
    }
  ]
}